git_glance/__init__.py
git_glance/config.py
git_glance/git.py
git_glance/main.py
git_glance-1.3.0.dist-info/licenses/LICENSE
git_glance-1.3.0.dist-info/METADATA
git_glance-1.3.0.dist-info/WHEEL
git_glance-1.3.0.dist-info/entry_points.txt
git_glance-1.3.0.dist-info/top_level.txt
git_glance-1.3.0.dist-info/RECORD
