Metadata-Version: 2.4
Name: git-glance
Version: 1.3.0
Summary: A CLI tool to track multiple Git repositories
Author: Harshit Thota
Project-URL: Homepage, https://github.com/harsh-thota/Git-Glance
Project-URL: Repository, https://github.com/harsh-thota/Git-Glance.git
Project-URL: Documentation, https://github.com/harsh-thota/Git-Glance#readme
Keywords: git,cli,tool,rich,typer
Classifier: Programming Language :: Python :: 3
Classifier: Operating System :: OS Independent
Requires-Python: >=3.7
License-File: LICENSE
Requires-Dist: typer[all]>=0.9.0
Requires-Dist: rich>=13.0.0
Requires-Dist: platformdirs>=2.5
Dynamic: license-file
